Metadata-Version: 2.4
Name: idptools-starling
Version: 2.0.0a3
Summary: Construction of intrinsically disordered proteins ensembles through multiscale generative models
Author-email: Borna Novak <bnovak@wustl.edu>
License: MIT
Classifier: License :: OSI Approved :: MIT License
Classifier: Programming Language :: Python :: 3
Requires-Python: >=3.8
License-File: LICENSE
Requires-Dist: numpy>=1.26
Requires-Dist: torch
Requires-Dist: scipy
Requires-Dist: cython>=3.0.0
Requires-Dist: matplotlib
Requires-Dist: jupyter
Requires-Dist: ipython
Requires-Dist: pytorch-lightning
Requires-Dist: scikit-learn
Requires-Dist: einops
Requires-Dist: tqdm
Requires-Dist: PyYAML
Requires-Dist: h5py
Requires-Dist: pandas
Requires-Dist: pytest
Requires-Dist: protfasta
Requires-Dist: soursop
Requires-Dist: hdf5plugin
Requires-Dist: mdtraj>=1.9.7
Requires-Dist: metapredict>=3.0
Requires-Dist: faiss-cpu>=1.7.4
Requires-Dist: zstandard>=0.22
Provides-Extra: search-gpu
Requires-Dist: faiss-gpu>=1.7.4; extra == "search-gpu"
Provides-Extra: test
Requires-Dist: pytest>=6.1.2; extra == "test"
Requires-Dist: pytest-runner; extra == "test"
Dynamic: license-file
